dst/dev/__init__.py
dst/dev/py.typed
dst/dev/cli/__init__.py
dst/dev/cli/program.py
dst/dev/options/__init__.py
dst/dev/options/coverage.py
dst/dev/options/isort.py
dst/dev/options/mypy.py
dst/dev/options/pep8.py
dst/dev/options/pylint.py
dst/dev/options/pytest.py
dst/dev/options/utils.py
dst/dev/options/yapf.py
dst.dev-2021.1a0.dist-info/LICENSE
dst.dev-2021.1a0.dist-info/METADATA
dst.dev-2021.1a0.dist-info/WHEEL
dst.dev-2021.1a0.dist-info/entry_points.txt
dst.dev-2021.1a0.dist-info/top_level.txt
dst.dev-2021.1a0.dist-info/RECORD
