Metadata-Version: 2.1
Name: dst.dev
Version: 2021.1a0
Summary: UNKNOWN
Home-page: https://gitlab.com/pydst/dev
Author: DST Owl
Author-email: owl.dst@gmail.com
Maintainer: DST Owl
Maintainer-email: owl.dst@gmail.com
License: MIT
Platform: any
Classifier: Development Status :: 3 - Alpha
Classifier: Intended Audience :: Developers
Classifier: Intended Audience :: Information Technology
Classifier: License :: OSI Approved :: MIT License
Classifier: Programming Language :: Python
Classifier: Programming Language :: Python :: 3
Classifier: Programming Language :: Python :: 3 :: Only
Classifier: Programming Language :: Python :: 3.8
Classifier: Programming Language :: Python :: 3.9
Classifier: Programming Language :: Python :: 3.10
Classifier: Topic :: Software Development
Classifier: Topic :: Utilities
Classifier: Typing :: Typed
Requires-Python: >=3.8
License-File: LICENSE
Requires-Dist: flake8
Requires-Dist: isort
Requires-Dist: yapf
Requires-Dist: pycodestyle
Requires-Dist: pylint (<2.12)
Requires-Dist: pylint-json2html
Requires-Dist: mypy
Requires-Dist: pytest-cov
Requires-Dist: pytest-html
Requires-Dist: types-pkg-resources
Requires-Dist: hiddenv
Provides-Extra: dev
